littleutils/__init__.py
littleutils/version.py
littleutils-0.2.4.dist-info/LICENSE
littleutils-0.2.4.dist-info/METADATA
littleutils-0.2.4.dist-info/WHEEL
littleutils-0.2.4.dist-info/top_level.txt
littleutils-0.2.4.dist-info/RECORD
